python_utilities/__init__.py
python_utilities/io_tools.py
python_utilities/parallel.py
python_utilities/scripting.py
python_utilities/plotting/__init__.py
python_utilities/plotting/color_cycles.py
python_utilities/plotting/styles.py
python_utilities/plotting/util.py
sdaxen_python_utilities-0.1.5.dist-info/LICENSE.txt
sdaxen_python_utilities-0.1.5.dist-info/METADATA
sdaxen_python_utilities-0.1.5.dist-info/WHEEL
sdaxen_python_utilities-0.1.5.dist-info/top_level.txt
sdaxen_python_utilities-0.1.5.dist-info/RECORD
