Metadata-Version: 2.1
Name: sdaxen_python_utilities
Version: 0.1.5
Summary: A collection of useful tools for common Python tasks
Home-page: https://github.com/sdaxen/python_utilities
Author: Seth Axen
Author-email: seth.axen@gmail.com
License: MIT
Download-URL: https://github.com/sdaxen/python_utilities/tarball/0.1.4
Keywords: parallelization,scripting,logging,io,plotting
Platform: UNKNOWN
Classifier: Programming Language :: Python
Classifier: Programming Language :: Python :: 2.7
Classifier: Programming Language :: Python :: 3.6
Classifier: License :: OSI Approved :: MIT License
Classifier: Operating System :: OS Independent
Classifier: Development Status :: 4 - Beta
Classifier: Intended Audience :: Developers
Classifier: Intended Audience :: System Administrators
Classifier: Intended Audience :: Science/Research
Classifier: Intended Audience :: Education
Classifier: Topic :: Scientific/Engineering
Classifier: Topic :: Software Development :: Libraries :: Python Modules
Classifier: Topic :: System :: Distributed Computing
Classifier: Topic :: System :: Logging
Classifier: Topic :: Utilities
License-File: LICENSE.txt
